setup.py
unimatrix.ext.one.egg-info/PKG-INFO
unimatrix.ext.one.egg-info/SOURCES.txt
unimatrix.ext.one.egg-info/dependency_links.txt
unimatrix.ext.one.egg-info/requires.txt
unimatrix.ext.one.egg-info/top_level.txt
unimatrix/ext/one/__init__.py